setuptools_odoo/__init__.py
setuptools_odoo/addons-10c.txt
setuptools_odoo/addons-10e.txt
setuptools_odoo/addons-11c.txt
setuptools_odoo/addons-11e.txt
setuptools_odoo/addons-12c.txt
setuptools_odoo/addons-12e.txt
setuptools_odoo/addons-13c.txt
setuptools_odoo/addons-13e.txt
setuptools_odoo/addons-14c.txt
setuptools_odoo/addons-14e.txt
setuptools_odoo/addons-15c.txt
setuptools_odoo/addons-15e.txt
setuptools_odoo/addons-16c.txt
setuptools_odoo/addons-16e.txt
setuptools_odoo/addons-7c.txt
setuptools_odoo/addons-8c.txt
setuptools_odoo/addons-9c.txt
setuptools_odoo/addons-9e.txt
setuptools_odoo/base_addons.py
setuptools_odoo/commands.py
setuptools_odoo/core.py
setuptools_odoo/external_dependencies.py
setuptools_odoo/get_requirements.py
setuptools_odoo/git_postversion.py
setuptools_odoo/make_default_setup.py
setuptools_odoo/manifest.py
setuptools_odoo/setup_keywords.py
setuptools_odoo-3.3.1.dist-info/licenses/LICENSE
setuptools_odoo-3.3.1.dist-info/METADATA
setuptools_odoo-3.3.1.dist-info/WHEEL
setuptools_odoo-3.3.1.dist-info/entry_points.txt
setuptools_odoo-3.3.1.dist-info/top_level.txt
setuptools_odoo-3.3.1.dist-info/RECORD
