Metadata-Version: 2.4
Name: setuptools-odoo
Version: 3.3.1
Summary: A library to help package Odoo addons with setuptools
Home-page: http://github.com/acsone/setuptools-odoo
Author: ACSONE SA/NV
Author-email: info@acsone.eu
License: LGPLv3
Classifier: Development Status :: 5 - Production/Stable
Classifier: Intended Audience :: Developers
Classifier: License :: OSI Approved :: GNU Lesser General Public License v3 (LGPLv3)
Classifier: Operating System :: POSIX
Classifier: Programming Language :: Python
Classifier: Framework :: Odoo
Requires-Python: >=2.7, !=3.0.*, !=3.1.*, !=3.2.*, !=3.3.*, !=3.4.*
License-File: LICENSE
Requires-Dist: setuptools
Requires-Dist: setuptools_scm!=4.0.0,>=2.1
Dynamic: author
Dynamic: author-email
Dynamic: classifier
Dynamic: description
Dynamic: home-page
Dynamic: license
Dynamic: license-file
Dynamic: requires-dist
Dynamic: requires-python
Dynamic: summary
